MyTMC_2209/TMC_2209_StepperDriver.py
MyTMC_2209/_TMC_2209_comm.py
MyTMC_2209/_TMC_2209_logger.py
MyTMC_2209/_TMC_2209_move.py
MyTMC_2209/_TMC_2209_test.py
MyTMC_2209/__init__.py
dip_coater/__init__.py
dip_coater/app.py
dip_coater/app_state.py
dip_coater/code_editor_init_content.py
dip_coater/coder_API.md
dip_coater/constants.py
dip_coater/gpio.py
dip_coater/help.md
dip_coater/tui.tcss
dip_coater/commands/__init__.py
dip_coater/commands/help_command.py
dip_coater/logging/__init__.py
dip_coater/logging/motor_logger.py
dip_coater/motor/__init__.py
dip_coater/motor/tmc2209.py
dip_coater/screens/__init__.py
dip_coater/screens/help_screen.py
dip_coater/utils/__init__.py
dip_coater/utils/helpers.py
dip_coater/utils/threading_util.py
dip_coater/widgets/__init__.py
dip_coater/widgets/advanced_settings.py
dip_coater/widgets/coder.py
dip_coater/widgets/distance_controls.py
dip_coater/widgets/motor_controls.py
dip_coater/widgets/position_controls.py
dip_coater/widgets/speed_controls.py
dip_coater/widgets/status.py
dip_coater/widgets/status_advanced.py
dip_coater/widgets/step_mode.py
dip_coater/widgets/tabs/__init__.py
dip_coater/widgets/tabs/advanced_settings_tab.py
dip_coater/widgets/tabs/coder_tab.py
dip_coater/widgets/tabs/logs_tab.py
dip_coater/widgets/tabs/main_tab.py
test/test_gpiozero.py
dip_coater-1.0.0.dist-info/METADATA
dip_coater-1.0.0.dist-info/WHEEL
dip_coater-1.0.0.dist-info/entry_points.txt
dip_coater-1.0.0.dist-info/top_level.txt
dip_coater-1.0.0.dist-info/RECORD
