Metadata-Version: 2.1
Name: dip-coater
Version: 1.0.0
Author-email: Rik Huygen <rik.huygen@kuleuven.be>, Sibo Van Gool <sibo.vangool@kuleuven.be>
License: MIT License
Project-URL: repository, https://github.com/IvS-KULeuven/dip_coater
Classifier: Programming Language :: Python :: 3
Classifier: Programming Language :: Python :: 3.9
Classifier: Programming Language :: Python :: 3.10
Classifier: Programming Language :: Python :: 3.11
Classifier: License :: OSI Approved :: MIT License
Requires-Python: <4.0,>=3.8
Requires-Dist: textual >=0.73.0
Requires-Dist: textual-dev
Requires-Dist: uvloop >=0.19.0
Provides-Extra: rpi
Requires-Dist: RPi.GPIO ; extra == 'rpi'
Requires-Dist: TMC-2209-Raspberry-Pi >=0.5.1 ; extra == 'rpi'
